fireTS/core.py
fireTS/models.py
fireTS/utils.py
fireTS-0.0.9.dist-info/LICENSE
fireTS-0.0.9.dist-info/METADATA
fireTS-0.0.9.dist-info/WHEEL
fireTS-0.0.9.dist-info/top_level.txt
fireTS-0.0.9.dist-info/RECORD
