Metadata-Version: 2.1
Name: fireTS
Version: 0.0.9
Summary: A python package for multi-variate time series prediction
Home-page: https://github.com/jxx123/fireTS.git
Author: Jinyu Xie
Author-email: xjygr08@gmail.com
License: MIT
License-File: LICENSE
Requires-Dist: numpy
Requires-Dist: scipy
Requires-Dist: scikit-learn (==1.2.1)
